{
  "config": {
    "configFile": "D:\\LearnPlaywrightB33\\playwright.config.js",
    "rootDir": "D:/LearnPlaywrightB33/tests",
    "forbidOnly": false,
    "fullyParallel": false,
    "globalSetup": null,
    "globalTeardown": null,
    "globalTimeout": 3600000,
    "grep": {},
    "grepInvert": null,
    "maxFailures": 0,
    "metadata": {
      "actualWorkers": 1
    },
    "preserveOutput": "always",
    "reporter": [
      [
        "html",
        null
      ],
      [
        "list",
        null
      ],
      [
        "json",
        {
          "outputFile": "results.json"
        }
      ],
      [
        "D:\\LearnPlaywrightB33\\node_modules\\allure-playwright\\dist\\cjs\\index.js",
        null
      ]
    ],
    "reportSlowTests": {
      "max": 5,
      "threshold": 300000
    },
    "quiet": false,
    "projects": [
      {
        "outputDir": "D:/LearnPlaywrightB33/test-results",
        "repeatEach": 1,
        "retries": 0,
        "metadata": {
          "actualWorkers": 1
        },
        "id": "Microsoft Edge",
        "name": "Microsoft Edge",
        "testDir": "D:/LearnPlaywrightB33/tests",
        "testIgnore": [],
        "testMatch": [
          "**/*.@(spec|test).?(c|m)[jt]s?(x)"
        ],
        "timeout": 40000
      }
    ],
    "shard": null,
    "tags": [],
    "updateSnapshots": "missing",
    "updateSourceMethod": "3way",
    "version": "1.57.0",
    "workers": 1,
    "webServer": null
  },
  "suites": [
    {
      "title": "swaglogintest.spec.js",
      "file": "swaglogintest.spec.js",
      "column": 0,
      "line": 0,
      "specs": [],
      "suites": [
        {
          "title": "Swag Labs Login Tests",
          "file": "swaglogintest.spec.js",
          "line": 5,
          "column": 6,
          "specs": [],
          "suites": [
            {
              "title": "Login with different credentials",
              "file": "swaglogintest.spec.js",
              "line": 18,
              "column": 8,
              "specs": [
                {
                  "title": "Verify login to Swaglabs Valid Credentials",
                  "ok": true,
                  "tags": [],
                  "tests": [
                    {
                      "timeout": 40000,
                      "annotations": [],
                      "expectedStatus": "passed",
                      "projectId": "Microsoft Edge",
                      "projectName": "Microsoft Edge",
                      "results": [
                        {
                          "workerIndex": 3,
                          "parallelIndex": 0,
                          "status": "passed",
                          "duration": 4287,
                          "errors": [],
                          "stdout": [],
                          "stderr": [],
                          "retry": 0,
                          "startTime": "2026-01-26T05:45:00.479Z",
                          "annotations": [],
                          "attachments": [
                            {
                              "name": "screenshot",
                              "contentType": "image/png",
                              "path": "D:\\LearnPlaywrightB33\\test-results\\swaglogintest-Swag-Labs-Lo-cba3d--Swaglabs-Valid-Credentials-Microsoft-Edge\\test-finished-1.png"
                            }
                          ]
                        }
                      ],
                      "status": "expected"
                    }
                  ],
                  "id": "8206cccaa4726b3bbdba-eb1610490f73c2b89130",
                  "file": "swaglogintest.spec.js",
                  "line": 20,
                  "column": 11
                },
                {
                  "title": "Verify login to Swaglabs Invalid Username",
                  "ok": true,
                  "tags": [],
                  "tests": [
                    {
                      "timeout": 40000,
                      "annotations": [],
                      "expectedStatus": "passed",
                      "projectId": "Microsoft Edge",
                      "projectName": "Microsoft Edge",
                      "results": [
                        {
                          "workerIndex": 3,
                          "parallelIndex": 0,
                          "status": "passed",
                          "duration": 3929,
                          "errors": [],
                          "stdout": [],
                          "stderr": [],
                          "retry": 0,
                          "startTime": "2026-01-26T05:45:04.901Z",
                          "annotations": [],
                          "attachments": [
                            {
                              "name": "screenshot",
                              "contentType": "image/png",
                              "path": "D:\\LearnPlaywrightB33\\test-results\\swaglogintest-Swag-Labs-Lo-57409-o-Swaglabs-Invalid-Username-Microsoft-Edge\\test-finished-1.png"
                            }
                          ]
                        }
                      ],
                      "status": "expected"
                    }
                  ],
                  "id": "8206cccaa4726b3bbdba-d94b0d2de4711c36f283",
                  "file": "swaglogintest.spec.js",
                  "line": 20,
                  "column": 11
                },
                {
                  "title": "Verify login to Swaglabs Invalid Password",
                  "ok": true,
                  "tags": [],
                  "tests": [
                    {
                      "timeout": 40000,
                      "annotations": [],
                      "expectedStatus": "passed",
                      "projectId": "Microsoft Edge",
                      "projectName": "Microsoft Edge",
                      "results": [
                        {
                          "workerIndex": 3,
                          "parallelIndex": 0,
                          "status": "passed",
                          "duration": 3081,
                          "errors": [],
                          "stdout": [],
                          "stderr": [],
                          "retry": 0,
                          "startTime": "2026-01-26T05:45:08.885Z",
                          "annotations": [],
                          "attachments": [
                            {
                              "name": "screenshot",
                              "contentType": "image/png",
                              "path": "D:\\LearnPlaywrightB33\\test-results\\swaglogintest-Swag-Labs-Lo-8a61f-o-Swaglabs-Invalid-Password-Microsoft-Edge\\test-finished-1.png"
                            }
                          ]
                        }
                      ],
                      "status": "expected"
                    }
                  ],
                  "id": "8206cccaa4726b3bbdba-e003c87adf41184c6361",
                  "file": "swaglogintest.spec.js",
                  "line": 20,
                  "column": 11
                },
                {
                  "title": "Verify login to Swaglabs Both Invalid Credentials",
                  "ok": true,
                  "tags": [],
                  "tests": [
                    {
                      "timeout": 40000,
                      "annotations": [],
                      "expectedStatus": "passed",
                      "projectId": "Microsoft Edge",
                      "projectName": "Microsoft Edge",
                      "results": [
                        {
                          "workerIndex": 3,
                          "parallelIndex": 0,
                          "status": "passed",
                          "duration": 2936,
                          "errors": [],
                          "stdout": [],
                          "stderr": [],
                          "retry": 0,
                          "startTime": "2026-01-26T05:45:12.049Z",
                          "annotations": [],
                          "attachments": [
                            {
                              "name": "screenshot",
                              "contentType": "image/png",
                              "path": "D:\\LearnPlaywrightB33\\test-results\\swaglogintest-Swag-Labs-Lo-eb527-bs-Both-Invalid-Credentials-Microsoft-Edge\\test-finished-1.png"
                            }
                          ]
                        }
                      ],
                      "status": "expected"
                    }
                  ],
                  "id": "8206cccaa4726b3bbdba-18158ffd3e376d67a4e5",
                  "file": "swaglogintest.spec.js",
                  "line": 20,
                  "column": 11
                },
                {
                  "title": "Verify login to Swaglabs Locked Out User",
                  "ok": true,
                  "tags": [],
                  "tests": [
                    {
                      "timeout": 40000,
                      "annotations": [],
                      "expectedStatus": "passed",
                      "projectId": "Microsoft Edge",
                      "projectName": "Microsoft Edge",
                      "results": [
                        {
                          "workerIndex": 3,
                          "parallelIndex": 0,
                          "status": "passed",
                          "duration": 3081,
                          "errors": [],
                          "stdout": [],
                          "stderr": [],
                          "retry": 0,
                          "startTime": "2026-01-26T05:45:15.017Z",
                          "annotations": [],
                          "attachments": [
                            {
                              "name": "screenshot",
                              "contentType": "image/png",
                              "path": "D:\\LearnPlaywrightB33\\test-results\\swaglogintest-Swag-Labs-Lo-7aa05-to-Swaglabs-Locked-Out-User-Microsoft-Edge\\test-finished-1.png"
                            }
                          ]
                        }
                      ],
                      "status": "expected"
                    }
                  ],
                  "id": "8206cccaa4726b3bbdba-7c6335b6d8a57c9331af",
                  "file": "swaglogintest.spec.js",
                  "line": 20,
                  "column": 11
                }
              ]
            }
          ]
        }
      ]
    }
  ],
  "errors": [],
  "stats": {
    "startTime": "2026-01-26T05:44:57.033Z",
    "duration": 21165.18200000003,
    "expected": 5,
    "skipped": 0,
    "unexpected": 0,
    "flaky": 0
  }
}